FTIRbackgroundsubtract/__init__.py
FTIRbackgroundsubtract/core.py
FTIR_background_subtract-1.2.0.dist-info/LICENSE
FTIR_background_subtract-1.2.0.dist-info/METADATA
FTIR_background_subtract-1.2.0.dist-info/WHEEL
FTIR_background_subtract-1.2.0.dist-info/top_level.txt
FTIR_background_subtract-1.2.0.dist-info/RECORD
