Metadata-Version: 2.1
Name: FTIR-background-subtract
Version: 1.2.0
Summary: A GUI tool for drawing polynomial backgrounds on FTIR spectra and subtracting them to get total absorbance (by height) of a desired peak.
Home-page: https://github.com/kaylai/ftir-background-subtract
Author: Kayla Iacovino and Nial
Author-email: kaylaiacovino@gmail.com
License: UNKNOWN
Platform: UNKNOWN
Classifier: Programming Language :: Python :: 3
Classifier: License :: OSI Approved :: MIT License
Classifier: Operating System :: OS Independent
Requires-Python: >=3.6
Requires-Dist: numpy
Requires-Dist: matplotlib
Requires-Dist: wxPython
